vo_distributions/Binomialdistribution.py
vo_distributions/Gaussiandistribution.py
vo_distributions/Generaldistribution.py
vo_distributions/__init__.py
vo_distributions-1.0.dist-info/METADATA
vo_distributions-1.0.dist-info/WHEEL
vo_distributions-1.0.dist-info/top_level.txt
vo_distributions-1.0.dist-info/RECORD
