Metadata-Version: 2.1
Name: vo_distributions
Version: 1.0
Summary: Gaussian and Binomial distributions
Author: Vivien Ogoun
Author-email: vivien.developer@gmail.com
